manim_onlinetex/__init__.py
manim_onlinetex/manim_onlinetex.py
manim_onlinetex-0.2.0.dist-info/entry_points.txt
manim_onlinetex-0.2.0.dist-info/LICENSE.txt
manim_onlinetex-0.2.0.dist-info/WHEEL
manim_onlinetex-0.2.0.dist-info/METADATA
manim_onlinetex-0.2.0.dist-info/RECORD
