Metadata-Version: 2.1
Name: manim-onlinetex
Version: 0.2.0
Summary: A Manim Plugin that renders LaTeX for Mobjects like Tex and MathTex via online services.
Home-page: https://github.com/ManimCommunity/manim-onlinetex
License: MIT
Author: The Manim Community Developers
Requires-Python: >=3.6.2,<4.0.0
Classifier: Development Status :: 4 - Beta
Classifier: License :: OSI Approved :: MIT License
Classifier: Natural Language :: English
Classifier: Programming Language :: Python :: 3
Classifier: Programming Language :: Python :: 3.10
Classifier: Programming Language :: Python :: 3.6
Classifier: Programming Language :: Python :: 3.7
Classifier: Programming Language :: Python :: 3.8
Classifier: Programming Language :: Python :: 3.9
Classifier: Topic :: Multimedia :: Graphics
Classifier: Topic :: Multimedia :: Video
Classifier: Topic :: Scientific/Engineering
Requires-Dist: manim
Requires-Dist: requests
Project-URL: Repository, https://github.com/ManimCommunity/manim-onlinetex
